toolky/__init__.py
toolky/misc.py
toolky/cli/__init__.py
toolky/cli/search.py
toolky/core/__init__.py
toolky/core/mp.py
toolky-0.1.2.0.dist-info/LICENSE
toolky-0.1.2.0.dist-info/METADATA
toolky-0.1.2.0.dist-info/WHEEL
toolky-0.1.2.0.dist-info/entry_points.txt
toolky-0.1.2.0.dist-info/top_level.txt
toolky-0.1.2.0.dist-info/RECORD
